bin/__init__.py
hammr/__init__.py
hammr/hammr.py
hammr/commands/__init__.py
hammr/commands/account/__init__.py
hammr/commands/account/account.py
hammr/commands/bundle/__init__.py
hammr/commands/bundle/bundle.py
hammr/commands/format/__init__.py
hammr/commands/format/format.py
hammr/commands/image/__init__.py
hammr/commands/image/image.py
hammr/commands/os/__init__.py
hammr/commands/os/os.py
hammr/commands/platform/__init__.py
hammr/commands/platform/platform.py
hammr/commands/quota/__init__.py
hammr/commands/quota/quota.py
hammr/commands/scan/__init__.py
hammr/commands/scan/scan.py
hammr/commands/template/__init__.py
hammr/commands/template/template.py
hammr/commands/user/__init__.py
hammr/commands/user/user.py
hammr/utils/__init__.py
hammr/utils/account_utils.py
hammr/utils/constants.py
hammr/utils/generate_utils.py
hammr/utils/hammr_utils.py
hammr/utils/publish_utils.py
hammr/utils/scan_utils.py
hammr_3.6-3.8.0.7rc1.data/scripts/hammr
hammr_3.6-3.8.0.7rc1.data/scripts/hammr.bat
hammr_3.6-3.8.0.7rc1.dist-info/DESCRIPTION.rst
hammr_3.6-3.8.0.7rc1.dist-info/METADATA
hammr_3.6-3.8.0.7rc1.dist-info/RECORD
hammr_3.6-3.8.0.7rc1.dist-info/WHEEL
hammr_3.6-3.8.0.7rc1.dist-info/metadata.json
hammr_3.6-3.8.0.7rc1.dist-info/top_level.txt
tests/__init__.py
tests/unit/__init__.py
tests/unit/commands/__init__.py
tests/unit/commands/template/__init__.py
tests/unit/commands/template/test_template.py
tests/unit/utils/__init__.py
